qbx/__init__.py
qbx/add_version.py
qbx/add_version_test.py
qbx/auth_wrapper.py
qbx/build_curdir.py
qbx/cdi.py
qbx/check_env.py
qbx/haproxy.py
qbx/kube_start.py
qbx/pull.py
qbx/register_kong.py
qbx/register_kong_test.py
qbx/register_ws.py
qbx/register_ws_test.py
qbx/supervisor.py
qbx/update_package.py
qbx/upload.py
qbx/uproxy.py
qbx/util.py
qbx/watch_http.py
qbx/watch_http_test.py
qbx/watchgit.py
qbx-2019.3.18.0.dist-info/METADATA
qbx-2019.3.18.0.dist-info/WHEEL
qbx-2019.3.18.0.dist-info/entry_points.txt
qbx-2019.3.18.0.dist-info/top_level.txt
qbx-2019.3.18.0.dist-info/RECORD
