Metadata-Version: 2.1
Name: qbx
Version: 2019.3.18.0
Summary: Qbtrade Management Script
Home-page: https://github.com/qbtrade/qbx
Author: qbtrade
Author-email: admin@qbtrade.org
License: UNKNOWN
Platform: UNKNOWN
Requires-Dist: docopt
Requires-Dist: requests
Requires-Dist: flask
Requires-Dist: flask-restful
Requires-Dist: redis
